export_ast/__init__.py
export_ast/export_ast.py
export_ast-1.0.6.dist-info/LICENSE
export_ast-1.0.6.dist-info/METADATA
export_ast-1.0.6.dist-info/WHEEL
export_ast-1.0.6.dist-info/top_level.txt
export_ast-1.0.6.dist-info/RECORD
