Metadata-Version: 2.1
Name: export-ast
Version: 1.0.6
Summary: Export a Python AST to a dictionary.
Home-page: https://github.com/tom-draper/ast-export
Author: Tom Draper
Author-email: Tom Draper <tomjdraper1@gmail.com>
License: MIT License
Project-URL: repository, https://github.com/tom-draper/export-ast
Keywords: ast,abstract syntax trees,dict,export,json
Classifier: License :: OSI Approved :: MIT License
Classifier: Programming Language :: Python
Classifier: Programming Language :: Python :: 3
Requires-Python: >=3.6
License-File: LICENSE
Provides-Extra: build
Requires-Dist: build ; extra == 'build'
Requires-Dist: twine ; extra == 'build'
Provides-Extra: dev
Requires-Dist: pytest ; extra == 'dev'
